DESCRIPTION.rst
LICENSE
MANIFEST.in
README.md
setup.py
oide/__init__.py
oide/app.py
oide/settings.py
oide/urls.py
oide.egg-info/PKG-INFO
oide.egg-info/SOURCES.txt
oide.egg-info/dependency_links.txt
oide.egg-info/entry_points.txt
oide.egg-info/not-zip-safe
oide.egg-info/requires.txt
oide.egg-info/top_level.txt
oide/apps/__init__.py
oide/apps/codeeditor/__init__.py
oide/apps/codeeditor/settings.py
oide/apps/codeeditor/static/ace.controller.js
oide/apps/codeeditor/static/editor.css
oide/apps/codeeditor/static/editor.html
oide/apps/codeeditor/static/editor.js
oide/apps/codeeditor/static/editor.service.js
oide/apps/codeeditor/static/filetree-controls.controller.js
oide/apps/codeeditor/static/filetree.controller.js
oide/apps/codeeditor/static/filetree.service.js
oide/apps/codeeditor/static/settings.controller.js
oide/apps/codeeditor/static/tabs.controller.js
oide/apps/codeeditor/static/templates/ace.html
oide/apps/codeeditor/static/templates/close-unsaved-modal.html
oide/apps/codeeditor/static/templates/delete-modal.html
oide/apps/codeeditor/static/templates/filetree-controls.html
oide/apps/codeeditor/static/templates/filetree.html
oide/apps/codeeditor/static/templates/rename-modal.html
oide/apps/codeeditor/static/templates/saveas-modal.html
oide/apps/codeeditor/static/templates/settings.html
oide/apps/codeeditor/static/templates/tabs.html
oide/apps/codeeditor/tests/js/editor.service_test.js
oide/apps/codeeditor/tests/js/editortabs.controller.specs.js
oide/apps/codeeditor/tests/js/filetree.controller.spec.js
oide/apps/codeeditor/tests/js/filetree.service.spec.js
oide/apps/codeeditor/tests/js/settings.controller.spec.js
oide/apps/filebrowser/__init__.py
oide/apps/filebrowser/handlers.py
oide/apps/filebrowser/permissions.py
oide/apps/filebrowser/posixfs.py
oide/apps/filebrowser/settings.py
oide/apps/filebrowser/urls.py
oide/apps/filebrowser/mixins/__init__.py
oide/apps/filebrowser/mixins/fs_mixin.py
oide/apps/filebrowser/static/filebrowser.controller.js
oide/apps/filebrowser/static/filebrowser.css
oide/apps/filebrowser/static/filebrowser.html
oide/apps/filebrowser/static/filebrowser.js
oide/apps/filebrowser/static/filetree.controller.js
